{
  "appVue/index/js": "/appVue/index.bundle.e46752.js",
  "app/detail/index/js": "/app/detail/index.bundle.e46752.js",
  "appReact/index/js": "/appReact/index.bundle.e46752.js",
  "appVue/store/modules/index/js": "/appVue/store/modules/index.bundle.e46752.js",
  "appReact/app/reducers/index/js": "/appReact/app/reducers/index.bundle.e46752.js",
  "app/index/index/js": "/app/index/index.bundle.e46752.js",
  "appVue/store/index/js": "/appVue/store/index.bundle.e46752.js",
  "app/list/index/js": "/app/list/index.bundle.e46752.js",
  "app/gallery/index/js": "/app/gallery/index.bundle.e46752.js"
}